{"cameraMode":{"drawMode":0,"name":"Shaded","section":"Shading Mode"},"sceneLighting":true,"audioPlay":false,"sceneViewState":{"m_AlwaysRefresh":false,"showFog":true,"showSkybox":true,"showFlares":true,"showImageEffects":true,"showParticleSystems":true,"showVisualEffectGraphs":true,"m_FxEnabled":true},"in2DMode":false,"pivot":{"x":-5.65561056137085,"y":1.96510648727417,"z":0.561679482460022},"rotation":{"x":0.16283516585826875,"y":-0.636279821395874,"z":0.13982155919075013,"w":0.7410111427307129},"size":6.44861364364624,"orthographic":false}