{"cameraMode":{"drawMode":0,"name":"Shaded","section":"Shading Mode"},"sceneLighting":true,"audioPlay":false,"sceneViewState":{"m_AlwaysRefresh":false,"showFog":true,"showSkybox":true,"showFlares":true,"showImageEffects":true,"showParticleSystems":true,"showVisualEffectGraphs":true,"m_FxEnabled":true},"in2DMode":false,"pivot":{"x":0.9385409951210022,"y":0.5941340923309326,"z":-1.4059689044952393},"rotation":{"x":0.43337422609329226,"y":-0.34608548879623415,"z":0.18474650382995606,"w":0.8113717436790466},"size":3.996979236602783,"orthographic":false}